mcp_notmuch_sendmail/.python-version
mcp_notmuch_sendmail/__init__.py
mcp_notmuch_sendmail/core.py
mcp_notmuch_sendmail/email_template.j2
mcp_notmuch_sendmail/email_template_draft.j2
mcp_notmuch_sendmail/latex.css
mcp_notmuch_sendmail/notmuchlib.py
mcp_notmuch_sendmail/sendmail.py
mcp_notmuch_sendmail/server.py
mcp_notmuch_sendmail-2025.4.9.174710.dist-info/METADATA
mcp_notmuch_sendmail-2025.4.9.174710.dist-info/WHEEL
mcp_notmuch_sendmail-2025.4.9.174710.dist-info/entry_points.txt
mcp_notmuch_sendmail-2025.4.9.174710.dist-info/licenses/LICENSE
mcp_notmuch_sendmail-2025.4.9.174710.dist-info/RECORD
