Metadata-Version: 2.4
Name: mcp-notmuch-sendmail
Version: 2025.4.9.174710
Summary: A MCP server that reads email with notmuch and uses sendmail for LaTeX-enhanced email composition
Project-URL: Homepage, https://github.com/runekaagaard/mcp-notmuch-sendmail
Project-URL: Issues, https://github.com/runekaagaard/mcp-notmuch-sendmail/issues
Project-URL: Disussions, https://github.com/runekaagaard/mcp-notmuch-sendmail/discussions
Author: Rune Kaagaard
License-File: LICENSE
Classifier: Operating System :: OS Independent
Classifier: Programming Language :: Python :: 3
Requires-Python: ==3.10.*
Requires-Dist: bs4>=0.0.2
Requires-Dist: html2text>=2024.2.26
Requires-Dist: jinja2>=3.1.5
Requires-Dist: markdown-checklist>=0.4.4
Requires-Dist: markdown>=3.7
Requires-Dist: mcp[cli]==1.2.0
Requires-Dist: mdit-py-plugins>=0.4.2
Requires-Dist: notmuch>=0.29.2
Requires-Dist: pymdown-extensions>=10.14
